doesnt_git_easier/__init__.py
doesnt_git_easier/commit.py
doesnt_git_easier/config.py
doesnt_git_easier/file.py
doesnt_git_easier-0.0.4.dist-info/METADATA
doesnt_git_easier-0.0.4.dist-info/WHEEL
doesnt_git_easier-0.0.4.dist-info/top_level.txt
doesnt_git_easier-0.0.4.dist-info/RECORD
